nexus_databoard/Home.py
nexus_databoard/__init__.py
nexus_databoard/.streamlit/config.toml
nexus_databoard/common/__init__.py
nexus_databoard/common/config.py
nexus_databoard/common/email.py
nexus_databoard/common/page_config.py
nexus_databoard/components/__init__.py
nexus_databoard/components/download.py
nexus_databoard/components/table.py
nexus_databoard/data/__init__.py
nexus_databoard/data/db.py
nexus_databoard/data/google_sheets.py
nexus_databoard/pages/01_Example-1.py
nexus_databoard/pages/02_Example-2.py
nexus_databoard/pages/03_Example-3.py
nexus_databoard/pages/04_Example-4.py
nexus_databoard/pages/05_Example-5.py
nexus_databoard/pages/__init__.py
nexus_databoard-0.0.2.dist-info/METADATA
nexus_databoard-0.0.2.dist-info/WHEEL
nexus_databoard-0.0.2.dist-info/licenses/LICENSE
nexus_databoard-0.0.2.dist-info/RECORD
