Metadata-Version: 2.1
Name: nexus_databoard
Version: 0.0.2
Summary: An oppinionated data science project template for the Nexus platform. An abstraction over Streamlit.
Project-URL: Homepage, https://github.com/savantly-net/nexus-databoard
Project-URL: Bug Tracker, https://github.com/savantly-net/nexus-databoard/issues
Author-email: Jeremy Branham <jeremy@savantly.net>
License-File: LICENSE
Classifier: License :: OSI Approved :: MIT License
Classifier: Operating System :: OS Independent
Classifier: Programming Language :: Python :: 3
Requires-Python: >=3.7
